ttra/__init__.py
ttra/ttra.py
ttra-0.1.1.dist-info/LICENSE
ttra-0.1.1.dist-info/METADATA
ttra-0.1.1.dist-info/WHEEL
ttra-0.1.1.dist-info/top_level.txt
ttra-0.1.1.dist-info/RECORD
