Metadata-Version: 2.1
Name: ttra
Version: 0.1.1
Summary: Implementation of Time-proof Time-series Reduction Algorithm
Home-page: https://github.com/tomWitkowski/Time-proof-Time-series-Reduction-Algorithm
Author: Tomasz Witkowskit
Author-email: tomasz.witkowski1@edu.uekat.pl
Classifier: Programming Language :: Python :: 3
Classifier: License :: OSI Approved :: MIT License
Classifier: Operating System :: OS Independent
Requires-Python: >=3.5
License-File: LICENSE
